[{"arguments":["clang","-Wno-documentation-unknown-command","-Wno-unknown-warning-option","-Wno-unknown-pragmas","-nostdinc","-nostdinc++","-g","-std=gnu++1z","-Wall","-Wextra","-Wextra","-fexceptions","-mthreads","-fsyntax-only","-m64","--target=x86_64-w64-mingw32","-DUNICODE","-D_UNICODE","-DWIN32","-DMINGW_HAS_SECURE_API","-DQT_QML_DEBUG","-DQT_WIDGETS_LIB","-DQT_GUI_LIB","-DQT_NETWORK_LIB","-DQT_CORE_LIB","-DQT_NEEDS_QMAIN","-DQ_CREATOR_RUN","-IG:\\Games\\Tools\\QtCreator\\share\\qtcreator\\cplusplus\\wrappedMingwHeaders","-IG:\\Games\\Tools\\QtCreator\\share\\qtcreator\\cplusplus\\wrappedQtHeaders","-IG:\\Games\\Tools\\QtCreator\\share\\qtcreator\\cplusplus\\wrappedQtHeaders\\QtCore","-IC:\\WorkDir\\b\\komsomols_work\\Interface","-IG:\\Games\\6.5.0\\mingw_64\\include","-IG:\\Games\\6.5.0\\mingw_64\\include\\QtWidgets","-IG:\\Games\\6.5.0\\mingw_64\\include\\QtGui","-IG:\\Games\\6.5.0\\mingw_64\\include\\QtNetwork","-IG:\\Games\\6.5.0\\mingw_64\\include\\QtCore","-IC:\\WorkDir\\b\\komsomols_work\\build-Interface-Desktop_Qt_6_5_0_MinGW_64_bit-Debug\\debug","-IC:\\WorkDir\\b\\komsomols_work\\build-Interface-Desktop_Qt_6_5_0_MinGW_64_bit-Debug","-IG:\\Games\\6.5.0\\mingw_64\\mkspecs\\win32-g++","-isystem","G:\\Games\\Tools\\mingw1120_64\\lib\\gcc\\x86_64-w64-mingw32\\11.2.0\\include\\c++","-isystem","G:\\Games\\Tools\\mingw1120_64\\lib\\gcc\\x86_64-w64-mingw32\\11.2.0\\include\\c++\\x86_64-w64-mingw32","-isystem","G:\\Games\\Tools\\mingw1120_64\\lib\\gcc\\x86_64-w64-mingw32\\11.2.0\\include\\c++\\backward","-isystem","G:\\Games\\Tools\\QtCreator\\bin\\clang\\lib\\clang\\15.0.0\\include","-isystem","G:\\Games\\Tools\\mingw1120_64\\x86_64-w64-mingw32\\include","-fmessage-length=0","-fdiagnostics-show-note-include-stack","-fretain-comments-from-system-headers","-fmacro-backtrace-limit=0","-ferror-limit=1000","-x","c++","C:\\WorkDir\\b\\komsomols_work\\Interface\\main.cpp"],"directory":"C:/WorkDir/b/komsomols_work/build-Interface-Desktop_Qt_6_5_0_MinGW_64_bit-Debug/.qtc_clangd","file":"C:/WorkDir/b/komsomols_work/Interface/main.cpp"},{"arguments":["clang","-Wno-documentation-unknown-command","-Wno-unknown-warning-option","-Wno-unknown-pragmas","-nostdinc","-nostdinc++","-g","-std=gnu++1z","-Wall","-Wextra","-Wextra","-fexceptions","-mthreads","-fsyntax-only","-m64","--target=x86_64-w64-mingw32","-DUNICODE","-D_UNICODE","-DWIN32","-DMINGW_HAS_SECURE_API","-DQT_QML_DEBUG","-DQT_WIDGETS_LIB","-DQT_GUI_LIB","-DQT_NETWORK_LIB","-DQT_CORE_LIB","-DQT_NEEDS_QMAIN","-DQ_CREATOR_RUN","-IG:\\Games\\Tools\\QtCreator\\share\\qtcreator\\cplusplus\\wrappedMingwHeaders","-IG:\\Games\\Tools\\QtCreator\\share\\qtcreator\\cplusplus\\wrappedQtHeaders","-IG:\\Games\\Tools\\QtCreator\\share\\qtcreator\\cplusplus\\wrappedQtHeaders\\QtCore","-IC:\\WorkDir\\b\\komsomols_work\\Interface","-IG:\\Games\\6.5.0\\mingw_64\\include","-IG:\\Games\\6.5.0\\mingw_64\\include\\QtWidgets","-IG:\\Games\\6.5.0\\mingw_64\\include\\QtGui","-IG:\\Games\\6.5.0\\mingw_64\\include\\QtNetwork","-IG:\\Games\\6.5.0\\mingw_64\\include\\QtCore","-IC:\\WorkDir\\b\\komsomols_work\\build-Interface-Desktop_Qt_6_5_0_MinGW_64_bit-Debug\\debug","-IC:\\WorkDir\\b\\komsomols_work\\build-Interface-Desktop_Qt_6_5_0_MinGW_64_bit-Debug","-IG:\\Games\\6.5.0\\mingw_64\\mkspecs\\win32-g++","-isystem","G:\\Games\\Tools\\mingw1120_64\\lib\\gcc\\x86_64-w64-mingw32\\11.2.0\\include\\c++","-isystem","G:\\Games\\Tools\\mingw1120_64\\lib\\gcc\\x86_64-w64-mingw32\\11.2.0\\include\\c++\\x86_64-w64-mingw32","-isystem","G:\\Games\\Tools\\mingw1120_64\\lib\\gcc\\x86_64-w64-mingw32\\11.2.0\\include\\c++\\backward","-isystem","G:\\Games\\Tools\\QtCreator\\bin\\clang\\lib\\clang\\15.0.0\\include","-isystem","G:\\Games\\Tools\\mingw1120_64\\x86_64-w64-mingw32\\include","-fmessage-length=0","-fdiagnostics-show-note-include-stack","-fretain-comments-from-system-headers","-fmacro-backtrace-limit=0","-ferror-limit=1000","-x","c++","C:\\WorkDir\\b\\komsomols_work\\Interface\\mainwindow.cpp"],"directory":"C:/WorkDir/b/komsomols_work/build-Interface-Desktop_Qt_6_5_0_MinGW_64_bit-Debug/.qtc_clangd","file":"C:/WorkDir/b/komsomols_work/Interface/mainwindow.cpp"},{"arguments":["clang","-Wno-documentation-unknown-command","-Wno-unknown-warning-option","-Wno-unknown-pragmas","-nostdinc","-nostdinc++","-g","-std=gnu++1z","-Wall","-Wextra","-Wextra","-fexceptions","-mthreads","-fsyntax-only","-m64","--target=x86_64-w64-mingw32","-DUNICODE","-D_UNICODE","-DWIN32","-DMINGW_HAS_SECURE_API","-DQT_QML_DEBUG","-DQT_WIDGETS_LIB","-DQT_GUI_LIB","-DQT_NETWORK_LIB","-DQT_CORE_LIB","-DQT_NEEDS_QMAIN","-DQ_CREATOR_RUN","-IG:\\Games\\Tools\\QtCreator\\share\\qtcreator\\cplusplus\\wrappedMingwHeaders","-IG:\\Games\\Tools\\QtCreator\\share\\qtcreator\\cplusplus\\wrappedQtHeaders","-IG:\\Games\\Tools\\QtCreator\\share\\qtcreator\\cplusplus\\wrappedQtHeaders\\QtCore","-IC:\\WorkDir\\b\\komsomols_work\\Interface","-IG:\\Games\\6.5.0\\mingw_64\\include","-IG:\\Games\\6.5.0\\mingw_64\\include\\QtWidgets","-IG:\\Games\\6.5.0\\mingw_64\\include\\QtGui","-IG:\\Games\\6.5.0\\mingw_64\\include\\QtNetwork","-IG:\\Games\\6.5.0\\mingw_64\\include\\QtCore","-IC:\\WorkDir\\b\\komsomols_work\\build-Interface-Desktop_Qt_6_5_0_MinGW_64_bit-Debug\\debug","-IC:\\WorkDir\\b\\komsomols_work\\build-Interface-Desktop_Qt_6_5_0_MinGW_64_bit-Debug","-IG:\\Games\\6.5.0\\mingw_64\\mkspecs\\win32-g++","-isystem","G:\\Games\\Tools\\mingw1120_64\\lib\\gcc\\x86_64-w64-mingw32\\11.2.0\\include\\c++","-isystem","G:\\Games\\Tools\\mingw1120_64\\lib\\gcc\\x86_64-w64-mingw32\\11.2.0\\include\\c++\\x86_64-w64-mingw32","-isystem","G:\\Games\\Tools\\mingw1120_64\\lib\\gcc\\x86_64-w64-mingw32\\11.2.0\\include\\c++\\backward","-isystem","G:\\Games\\Tools\\QtCreator\\bin\\clang\\lib\\clang\\15.0.0\\include","-isystem","G:\\Games\\Tools\\mingw1120_64\\x86_64-w64-mingw32\\include","-fmessage-length=0","-fdiagnostics-show-note-include-stack","-fretain-comments-from-system-headers","-fmacro-backtrace-limit=0","-ferror-limit=1000","-x","c++","C:\\WorkDir\\b\\komsomols_work\\Interface\\registration.cpp"],"directory":"C:/WorkDir/b/komsomols_work/build-Interface-Desktop_Qt_6_5_0_MinGW_64_bit-Debug/.qtc_clangd","file":"C:/WorkDir/b/komsomols_work/Interface/registration.cpp"},{"arguments":["clang","-Wno-documentation-unknown-command","-Wno-unknown-warning-option","-Wno-unknown-pragmas","-nostdinc","-nostdinc++","-g","-std=gnu++1z","-Wall","-Wextra","-Wextra","-fexceptions","-mthreads","-fsyntax-only","-m64","--target=x86_64-w64-mingw32","-DUNICODE","-D_UNICODE","-DWIN32","-DMINGW_HAS_SECURE_API","-DQT_QML_DEBUG","-DQT_WIDGETS_LIB","-DQT_GUI_LIB","-DQT_NETWORK_LIB","-DQT_CORE_LIB","-DQT_NEEDS_QMAIN","-DQ_CREATOR_RUN","-IG:\\Games\\Tools\\QtCreator\\share\\qtcreator\\cplusplus\\wrappedMingwHeaders","-IG:\\Games\\Tools\\QtCreator\\share\\qtcreator\\cplusplus\\wrappedQtHeaders","-IG:\\Games\\Tools\\QtCreator\\share\\qtcreator\\cplusplus\\wrappedQtHeaders\\QtCore","-IC:\\WorkDir\\b\\komsomols_work\\Interface","-IG:\\Games\\6.5.0\\mingw_64\\include","-IG:\\Games\\6.5.0\\mingw_64\\include\\QtWidgets","-IG:\\Games\\6.5.0\\mingw_64\\include\\QtGui","-IG:\\Games\\6.5.0\\mingw_64\\include\\QtNetwork","-IG:\\Games\\6.5.0\\mingw_64\\include\\QtCore","-IC:\\WorkDir\\b\\komsomols_work\\build-Interface-Desktop_Qt_6_5_0_MinGW_64_bit-Debug\\debug","-IC:\\WorkDir\\b\\komsomols_work\\build-Interface-Desktop_Qt_6_5_0_MinGW_64_bit-Debug","-IG:\\Games\\6.5.0\\mingw_64\\mkspecs\\win32-g++","-isystem","G:\\Games\\Tools\\mingw1120_64\\lib\\gcc\\x86_64-w64-mingw32\\11.2.0\\include\\c++","-isystem","G:\\Games\\Tools\\mingw1120_64\\lib\\gcc\\x86_64-w64-mingw32\\11.2.0\\include\\c++\\x86_64-w64-mingw32","-isystem","G:\\Games\\Tools\\mingw1120_64\\lib\\gcc\\x86_64-w64-mingw32\\11.2.0\\include\\c++\\backward","-isystem","G:\\Games\\Tools\\QtCreator\\bin\\clang\\lib\\clang\\15.0.0\\include","-isystem","G:\\Games\\Tools\\mingw1120_64\\x86_64-w64-mingw32\\include","-fmessage-length=0","-fdiagnostics-show-note-include-stack","-fretain-comments-from-system-headers","-fmacro-backtrace-limit=0","-ferror-limit=1000","-x","c++","C:\\WorkDir\\b\\komsomols_work\\Interface\\secondtask.cpp"],"directory":"C:/WorkDir/b/komsomols_work/build-Interface-Desktop_Qt_6_5_0_MinGW_64_bit-Debug/.qtc_clangd","file":"C:/WorkDir/b/komsomols_work/Interface/secondtask.cpp"},{"arguments":["clang","-Wno-documentation-unknown-command","-Wno-unknown-warning-option","-Wno-unknown-pragmas","-nostdinc","-nostdinc++","-g","-std=gnu++1z","-Wall","-Wextra","-Wextra","-fexceptions","-mthreads","-fsyntax-only","-m64","--target=x86_64-w64-mingw32","-DUNICODE","-D_UNICODE","-DWIN32","-DMINGW_HAS_SECURE_API","-DQT_QML_DEBUG","-DQT_WIDGETS_LIB","-DQT_GUI_LIB","-DQT_NETWORK_LIB","-DQT_CORE_LIB","-DQT_NEEDS_QMAIN","-DQ_CREATOR_RUN","-IG:\\Games\\Tools\\QtCreator\\share\\qtcreator\\cplusplus\\wrappedMingwHeaders","-IG:\\Games\\Tools\\QtCreator\\share\\qtcreator\\cplusplus\\wrappedQtHeaders","-IG:\\Games\\Tools\\QtCreator\\share\\qtcreator\\cplusplus\\wrappedQtHeaders\\QtCore","-IC:\\WorkDir\\b\\komsomols_work\\Interface","-IG:\\Games\\6.5.0\\mingw_64\\include","-IG:\\Games\\6.5.0\\mingw_64\\include\\QtWidgets","-IG:\\Games\\6.5.0\\mingw_64\\include\\QtGui","-IG:\\Games\\6.5.0\\mingw_64\\include\\QtNetwork","-IG:\\Games\\6.5.0\\mingw_64\\include\\QtCore","-IC:\\WorkDir\\b\\komsomols_work\\build-Interface-Desktop_Qt_6_5_0_MinGW_64_bit-Debug\\debug","-IC:\\WorkDir\\b\\komsomols_work\\build-Interface-Desktop_Qt_6_5_0_MinGW_64_bit-Debug","-IG:\\Games\\6.5.0\\mingw_64\\mkspecs\\win32-g++","-isystem","G:\\Games\\Tools\\mingw1120_64\\lib\\gcc\\x86_64-w64-mingw32\\11.2.0\\include\\c++","-isystem","G:\\Games\\Tools\\mingw1120_64\\lib\\gcc\\x86_64-w64-mingw32\\11.2.0\\include\\c++\\x86_64-w64-mingw32","-isystem","G:\\Games\\Tools\\mingw1120_64\\lib\\gcc\\x86_64-w64-mingw32\\11.2.0\\include\\c++\\backward","-isystem","G:\\Games\\Tools\\QtCreator\\bin\\clang\\lib\\clang\\15.0.0\\include","-isystem","G:\\Games\\Tools\\mingw1120_64\\x86_64-w64-mingw32\\include","-fmessage-length=0","-fdiagnostics-show-note-include-stack","-fretain-comments-from-system-headers","-fmacro-backtrace-limit=0","-ferror-limit=1000","-x","c++","C:\\WorkDir\\b\\komsomols_work\\Interface\\consoleclientt.cpp"],"directory":"C:/WorkDir/b/komsomols_work/build-Interface-Desktop_Qt_6_5_0_MinGW_64_bit-Debug/.qtc_clangd","file":"C:/WorkDir/b/komsomols_work/Interface/consoleclientt.cpp"},{"arguments":["clang","-Wno-documentation-unknown-command","-Wno-unknown-warning-option","-Wno-unknown-pragmas","-nostdinc","-nostdinc++","-g","-std=gnu++1z","-Wall","-Wextra","-Wextra","-fexceptions","-mthreads","-fsyntax-only","-m64","--target=x86_64-w64-mingw32","-DUNICODE","-D_UNICODE","-DWIN32","-DMINGW_HAS_SECURE_API","-DQT_QML_DEBUG","-DQT_WIDGETS_LIB","-DQT_GUI_LIB","-DQT_NETWORK_LIB","-DQT_CORE_LIB","-DQT_NEEDS_QMAIN","-DQ_CREATOR_RUN","-IG:\\Games\\Tools\\QtCreator\\share\\qtcreator\\cplusplus\\wrappedMingwHeaders","-IG:\\Games\\Tools\\QtCreator\\share\\qtcreator\\cplusplus\\wrappedQtHeaders","-IG:\\Games\\Tools\\QtCreator\\share\\qtcreator\\cplusplus\\wrappedQtHeaders\\QtCore","-IC:\\WorkDir\\b\\komsomols_work\\Interface","-IG:\\Games\\6.5.0\\mingw_64\\include","-IG:\\Games\\6.5.0\\mingw_64\\include\\QtWidgets","-IG:\\Games\\6.5.0\\mingw_64\\include\\QtGui","-IG:\\Games\\6.5.0\\mingw_64\\include\\QtNetwork","-IG:\\Games\\6.5.0\\mingw_64\\include\\QtCore","-IC:\\WorkDir\\b\\komsomols_work\\build-Interface-Desktop_Qt_6_5_0_MinGW_64_bit-Debug\\debug","-IC:\\WorkDir\\b\\komsomols_work\\build-Interface-Desktop_Qt_6_5_0_MinGW_64_bit-Debug","-IG:\\Games\\6.5.0\\mingw_64\\mkspecs\\win32-g++","-isystem","G:\\Games\\Tools\\mingw1120_64\\lib\\gcc\\x86_64-w64-mingw32\\11.2.0\\include\\c++","-isystem","G:\\Games\\Tools\\mingw1120_64\\lib\\gcc\\x86_64-w64-mingw32\\11.2.0\\include\\c++\\x86_64-w64-mingw32","-isystem","G:\\Games\\Tools\\mingw1120_64\\lib\\gcc\\x86_64-w64-mingw32\\11.2.0\\include\\c++\\backward","-isystem","G:\\Games\\Tools\\QtCreator\\bin\\clang\\lib\\clang\\15.0.0\\include","-isystem","G:\\Games\\Tools\\mingw1120_64\\x86_64-w64-mingw32\\include","-fmessage-length=0","-fdiagnostics-show-note-include-stack","-fretain-comments-from-system-headers","-fmacro-backtrace-limit=0","-ferror-limit=1000","-x","c++","C:\\WorkDir\\b\\komsomols_work\\Interface\\taskswindow.cpp"],"directory":"C:/WorkDir/b/komsomols_work/build-Interface-Desktop_Qt_6_5_0_MinGW_64_bit-Debug/.qtc_clangd","file":"C:/WorkDir/b/komsomols_work/Interface/taskswindow.cpp"},{"arguments":["clang","-Wno-documentation-unknown-command","-Wno-unknown-warning-option","-Wno-unknown-pragmas","-nostdinc","-nostdinc++","-g","-std=gnu++1z","-Wall","-Wextra","-Wextra","-fexceptions","-mthreads","-fsyntax-only","-m64","--target=x86_64-w64-mingw32","-DUNICODE","-D_UNICODE","-DWIN32","-DMINGW_HAS_SECURE_API","-DQT_QML_DEBUG","-DQT_WIDGETS_LIB","-DQT_GUI_LIB","-DQT_NETWORK_LIB","-DQT_CORE_LIB","-DQT_NEEDS_QMAIN","-DQ_CREATOR_RUN","-IG:\\Games\\Tools\\QtCreator\\share\\qtcreator\\cplusplus\\wrappedMingwHeaders","-IG:\\Games\\Tools\\QtCreator\\share\\qtcreator\\cplusplus\\wrappedQtHeaders","-IG:\\Games\\Tools\\QtCreator\\share\\qtcreator\\cplusplus\\wrappedQtHeaders\\QtCore","-IC:\\WorkDir\\b\\komsomols_work\\Interface","-IG:\\Games\\6.5.0\\mingw_64\\include","-IG:\\Games\\6.5.0\\mingw_64\\include\\QtWidgets","-IG:\\Games\\6.5.0\\mingw_64\\include\\QtGui","-IG:\\Games\\6.5.0\\mingw_64\\include\\QtNetwork","-IG:\\Games\\6.5.0\\mingw_64\\include\\QtCore","-IC:\\WorkDir\\b\\komsomols_work\\build-Interface-Desktop_Qt_6_5_0_MinGW_64_bit-Debug\\debug","-IC:\\WorkDir\\b\\komsomols_work\\build-Interface-Desktop_Qt_6_5_0_MinGW_64_bit-Debug","-IG:\\Games\\6.5.0\\mingw_64\\mkspecs\\win32-g++","-isystem","G:\\Games\\Tools\\mingw1120_64\\lib\\gcc\\x86_64-w64-mingw32\\11.2.0\\include\\c++","-isystem","G:\\Games\\Tools\\mingw1120_64\\lib\\gcc\\x86_64-w64-mingw32\\11.2.0\\include\\c++\\x86_64-w64-mingw32","-isystem","G:\\Games\\Tools\\mingw1120_64\\lib\\gcc\\x86_64-w64-mingw32\\11.2.0\\include\\c++\\backward","-isystem","G:\\Games\\Tools\\QtCreator\\bin\\clang\\lib\\clang\\15.0.0\\include","-isystem","G:\\Games\\Tools\\mingw1120_64\\x86_64-w64-mingw32\\include","-fmessage-length=0","-fdiagnostics-show-note-include-stack","-fretain-comments-from-system-headers","-fmacro-backtrace-limit=0","-ferror-limit=1000","-x","c++-header","C:\\WorkDir\\b\\komsomols_work\\Interface\\mainwindow.h"],"directory":"C:/WorkDir/b/komsomols_work/build-Interface-Desktop_Qt_6_5_0_MinGW_64_bit-Debug/.qtc_clangd","file":"C:/WorkDir/b/komsomols_work/Interface/mainwindow.h"},{"arguments":["clang","-Wno-documentation-unknown-command","-Wno-unknown-warning-option","-Wno-unknown-pragmas","-nostdinc","-nostdinc++","-g","-std=gnu++1z","-Wall","-Wextra","-Wextra","-fexceptions","-mthreads","-fsyntax-only","-m64","--target=x86_64-w64-mingw32","-DUNICODE","-D_UNICODE","-DWIN32","-DMINGW_HAS_SECURE_API","-DQT_QML_DEBUG","-DQT_WIDGETS_LIB","-DQT_GUI_LIB","-DQT_NETWORK_LIB","-DQT_CORE_LIB","-DQT_NEEDS_QMAIN","-DQ_CREATOR_RUN","-IG:\\Games\\Tools\\QtCreator\\share\\qtcreator\\cplusplus\\wrappedMingwHeaders","-IG:\\Games\\Tools\\QtCreator\\share\\qtcreator\\cplusplus\\wrappedQtHeaders","-IG:\\Games\\Tools\\QtCreator\\share\\qtcreator\\cplusplus\\wrappedQtHeaders\\QtCore","-IC:\\WorkDir\\b\\komsomols_work\\Interface","-IG:\\Games\\6.5.0\\mingw_64\\include","-IG:\\Games\\6.5.0\\mingw_64\\include\\QtWidgets","-IG:\\Games\\6.5.0\\mingw_64\\include\\QtGui","-IG:\\Games\\6.5.0\\mingw_64\\include\\QtNetwork","-IG:\\Games\\6.5.0\\mingw_64\\include\\QtCore","-IC:\\WorkDir\\b\\komsomols_work\\build-Interface-Desktop_Qt_6_5_0_MinGW_64_bit-Debug\\debug","-IC:\\WorkDir\\b\\komsomols_work\\build-Interface-Desktop_Qt_6_5_0_MinGW_64_bit-Debug","-IG:\\Games\\6.5.0\\mingw_64\\mkspecs\\win32-g++","-isystem","G:\\Games\\Tools\\mingw1120_64\\lib\\gcc\\x86_64-w64-mingw32\\11.2.0\\include\\c++","-isystem","G:\\Games\\Tools\\mingw1120_64\\lib\\gcc\\x86_64-w64-mingw32\\11.2.0\\include\\c++\\x86_64-w64-mingw32","-isystem","G:\\Games\\Tools\\mingw1120_64\\lib\\gcc\\x86_64-w64-mingw32\\11.2.0\\include\\c++\\backward","-isystem","G:\\Games\\Tools\\QtCreator\\bin\\clang\\lib\\clang\\15.0.0\\include","-isystem","G:\\Games\\Tools\\mingw1120_64\\x86_64-w64-mingw32\\include","-fmessage-length=0","-fdiagnostics-show-note-include-stack","-fretain-comments-from-system-headers","-fmacro-backtrace-limit=0","-ferror-limit=1000","-x","c++-header","C:\\WorkDir\\b\\komsomols_work\\Interface\\registration.h"],"directory":"C:/WorkDir/b/komsomols_work/build-Interface-Desktop_Qt_6_5_0_MinGW_64_bit-Debug/.qtc_clangd","file":"C:/WorkDir/b/komsomols_work/Interface/registration.h"},{"arguments":["clang","-Wno-documentation-unknown-command","-Wno-unknown-warning-option","-Wno-unknown-pragmas","-nostdinc","-nostdinc++","-g","-std=gnu++1z","-Wall","-Wextra","-Wextra","-fexceptions","-mthreads","-fsyntax-only","-m64","--target=x86_64-w64-mingw32","-DUNICODE","-D_UNICODE","-DWIN32","-DMINGW_HAS_SECURE_API","-DQT_QML_DEBUG","-DQT_WIDGETS_LIB","-DQT_GUI_LIB","-DQT_NETWORK_LIB","-DQT_CORE_LIB","-DQT_NEEDS_QMAIN","-DQ_CREATOR_RUN","-IG:\\Games\\Tools\\QtCreator\\share\\qtcreator\\cplusplus\\wrappedMingwHeaders","-IG:\\Games\\Tools\\QtCreator\\share\\qtcreator\\cplusplus\\wrappedQtHeaders","-IG:\\Games\\Tools\\QtCreator\\share\\qtcreator\\cplusplus\\wrappedQtHeaders\\QtCore","-IC:\\WorkDir\\b\\komsomols_work\\Interface","-IG:\\Games\\6.5.0\\mingw_64\\include","-IG:\\Games\\6.5.0\\mingw_64\\include\\QtWidgets","-IG:\\Games\\6.5.0\\mingw_64\\include\\QtGui","-IG:\\Games\\6.5.0\\mingw_64\\include\\QtNetwork","-IG:\\Games\\6.5.0\\mingw_64\\include\\QtCore","-IC:\\WorkDir\\b\\komsomols_work\\build-Interface-Desktop_Qt_6_5_0_MinGW_64_bit-Debug\\debug","-IC:\\WorkDir\\b\\komsomols_work\\build-Interface-Desktop_Qt_6_5_0_MinGW_64_bit-Debug","-IG:\\Games\\6.5.0\\mingw_64\\mkspecs\\win32-g++","-isystem","G:\\Games\\Tools\\mingw1120_64\\lib\\gcc\\x86_64-w64-mingw32\\11.2.0\\include\\c++","-isystem","G:\\Games\\Tools\\mingw1120_64\\lib\\gcc\\x86_64-w64-mingw32\\11.2.0\\include\\c++\\x86_64-w64-mingw32","-isystem","G:\\Games\\Tools\\mingw1120_64\\lib\\gcc\\x86_64-w64-mingw32\\11.2.0\\include\\c++\\backward","-isystem","G:\\Games\\Tools\\QtCreator\\bin\\clang\\lib\\clang\\15.0.0\\include","-isystem","G:\\Games\\Tools\\mingw1120_64\\x86_64-w64-mingw32\\include","-fmessage-length=0","-fdiagnostics-show-note-include-stack","-fretain-comments-from-system-headers","-fmacro-backtrace-limit=0","-ferror-limit=1000","-x","c++-header","C:\\WorkDir\\b\\komsomols_work\\Interface\\secondtask.h"],"directory":"C:/WorkDir/b/komsomols_work/build-Interface-Desktop_Qt_6_5_0_MinGW_64_bit-Debug/.qtc_clangd","file":"C:/WorkDir/b/komsomols_work/Interface/secondtask.h"},{"arguments":["clang","-Wno-documentation-unknown-command","-Wno-unknown-warning-option","-Wno-unknown-pragmas","-nostdinc","-nostdinc++","-g","-std=gnu++1z","-Wall","-Wextra","-Wextra","-fexceptions","-mthreads","-fsyntax-only","-m64","--target=x86_64-w64-mingw32","-DUNICODE","-D_UNICODE","-DWIN32","-DMINGW_HAS_SECURE_API","-DQT_QML_DEBUG","-DQT_WIDGETS_LIB","-DQT_GUI_LIB","-DQT_NETWORK_LIB","-DQT_CORE_LIB","-DQT_NEEDS_QMAIN","-DQ_CREATOR_RUN","-IG:\\Games\\Tools\\QtCreator\\share\\qtcreator\\cplusplus\\wrappedMingwHeaders","-IG:\\Games\\Tools\\QtCreator\\share\\qtcreator\\cplusplus\\wrappedQtHeaders","-IG:\\Games\\Tools\\QtCreator\\share\\qtcreator\\cplusplus\\wrappedQtHeaders\\QtCore","-IC:\\WorkDir\\b\\komsomols_work\\Interface","-IG:\\Games\\6.5.0\\mingw_64\\include","-IG:\\Games\\6.5.0\\mingw_64\\include\\QtWidgets","-IG:\\Games\\6.5.0\\mingw_64\\include\\QtGui","-IG:\\Games\\6.5.0\\mingw_64\\include\\QtNetwork","-IG:\\Games\\6.5.0\\mingw_64\\include\\QtCore","-IC:\\WorkDir\\b\\komsomols_work\\build-Interface-Desktop_Qt_6_5_0_MinGW_64_bit-Debug\\debug","-IC:\\WorkDir\\b\\komsomols_work\\build-Interface-Desktop_Qt_6_5_0_MinGW_64_bit-Debug","-IG:\\Games\\6.5.0\\mingw_64\\mkspecs\\win32-g++","-isystem","G:\\Games\\Tools\\mingw1120_64\\lib\\gcc\\x86_64-w64-mingw32\\11.2.0\\include\\c++","-isystem","G:\\Games\\Tools\\mingw1120_64\\lib\\gcc\\x86_64-w64-mingw32\\11.2.0\\include\\c++\\x86_64-w64-mingw32","-isystem","G:\\Games\\Tools\\mingw1120_64\\lib\\gcc\\x86_64-w64-mingw32\\11.2.0\\include\\c++\\backward","-isystem","G:\\Games\\Tools\\QtCreator\\bin\\clang\\lib\\clang\\15.0.0\\include","-isystem","G:\\Games\\Tools\\mingw1120_64\\x86_64-w64-mingw32\\include","-fmessage-length=0","-fdiagnostics-show-note-include-stack","-fretain-comments-from-system-headers","-fmacro-backtrace-limit=0","-ferror-limit=1000","-x","c++-header","C:\\WorkDir\\b\\komsomols_work\\Interface\\consoleclientt.h"],"directory":"C:/WorkDir/b/komsomols_work/build-Interface-Desktop_Qt_6_5_0_MinGW_64_bit-Debug/.qtc_clangd","file":"C:/WorkDir/b/komsomols_work/Interface/consoleclientt.h"},{"arguments":["clang","-Wno-documentation-unknown-command","-Wno-unknown-warning-option","-Wno-unknown-pragmas","-nostdinc","-nostdinc++","-g","-std=gnu++1z","-Wall","-Wextra","-Wextra","-fexceptions","-mthreads","-fsyntax-only","-m64","--target=x86_64-w64-mingw32","-DUNICODE","-D_UNICODE","-DWIN32","-DMINGW_HAS_SECURE_API","-DQT_QML_DEBUG","-DQT_WIDGETS_LIB","-DQT_GUI_LIB","-DQT_NETWORK_LIB","-DQT_CORE_LIB","-DQT_NEEDS_QMAIN","-DQ_CREATOR_RUN","-IG:\\Games\\Tools\\QtCreator\\share\\qtcreator\\cplusplus\\wrappedMingwHeaders","-IG:\\Games\\Tools\\QtCreator\\share\\qtcreator\\cplusplus\\wrappedQtHeaders","-IG:\\Games\\Tools\\QtCreator\\share\\qtcreator\\cplusplus\\wrappedQtHeaders\\QtCore","-IC:\\WorkDir\\b\\komsomols_work\\Interface","-IG:\\Games\\6.5.0\\mingw_64\\include","-IG:\\Games\\6.5.0\\mingw_64\\include\\QtWidgets","-IG:\\Games\\6.5.0\\mingw_64\\include\\QtGui","-IG:\\Games\\6.5.0\\mingw_64\\include\\QtNetwork","-IG:\\Games\\6.5.0\\mingw_64\\include\\QtCore","-IC:\\WorkDir\\b\\komsomols_work\\build-Interface-Desktop_Qt_6_5_0_MinGW_64_bit-Debug\\debug","-IC:\\WorkDir\\b\\komsomols_work\\build-Interface-Desktop_Qt_6_5_0_MinGW_64_bit-Debug","-IG:\\Games\\6.5.0\\mingw_64\\mkspecs\\win32-g++","-isystem","G:\\Games\\Tools\\mingw1120_64\\lib\\gcc\\x86_64-w64-mingw32\\11.2.0\\include\\c++","-isystem","G:\\Games\\Tools\\mingw1120_64\\lib\\gcc\\x86_64-w64-mingw32\\11.2.0\\include\\c++\\x86_64-w64-mingw32","-isystem","G:\\Games\\Tools\\mingw1120_64\\lib\\gcc\\x86_64-w64-mingw32\\11.2.0\\include\\c++\\backward","-isystem","G:\\Games\\Tools\\QtCreator\\bin\\clang\\lib\\clang\\15.0.0\\include","-isystem","G:\\Games\\Tools\\mingw1120_64\\x86_64-w64-mingw32\\include","-fmessage-length=0","-fdiagnostics-show-note-include-stack","-fretain-comments-from-system-headers","-fmacro-backtrace-limit=0","-ferror-limit=1000","-x","c++-header","C:\\WorkDir\\b\\komsomols_work\\Interface\\taskswindow.h"],"directory":"C:/WorkDir/b/komsomols_work/build-Interface-Desktop_Qt_6_5_0_MinGW_64_bit-Debug/.qtc_clangd","file":"C:/WorkDir/b/komsomols_work/Interface/taskswindow.h"},{"arguments":["clang","-Wno-documentation-unknown-command","-Wno-unknown-warning-option","-Wno-unknown-pragmas","-nostdinc","-nostdinc++","-g","-std=gnu++1z","-Wall","-Wextra","-Wextra","-fexceptions","-mthreads","-fsyntax-only","-m64","--target=x86_64-w64-mingw32","-DUNICODE","-D_UNICODE","-DWIN32","-DMINGW_HAS_SECURE_API","-DQT_QML_DEBUG","-DQT_WIDGETS_LIB","-DQT_GUI_LIB","-DQT_NETWORK_LIB","-DQT_CORE_LIB","-DQT_NEEDS_QMAIN","-DQ_CREATOR_RUN","-IG:\\Games\\Tools\\QtCreator\\share\\qtcreator\\cplusplus\\wrappedMingwHeaders","-IG:\\Games\\Tools\\QtCreator\\share\\qtcreator\\cplusplus\\wrappedQtHeaders","-IG:\\Games\\Tools\\QtCreator\\share\\qtcreator\\cplusplus\\wrappedQtHeaders\\QtCore","-IC:\\WorkDir\\b\\komsomols_work\\Interface","-IG:\\Games\\6.5.0\\mingw_64\\include","-IG:\\Games\\6.5.0\\mingw_64\\include\\QtWidgets","-IG:\\Games\\6.5.0\\mingw_64\\include\\QtGui","-IG:\\Games\\6.5.0\\mingw_64\\include\\QtNetwork","-IG:\\Games\\6.5.0\\mingw_64\\include\\QtCore","-IC:\\WorkDir\\b\\komsomols_work\\build-Interface-Desktop_Qt_6_5_0_MinGW_64_bit-Debug\\debug","-IC:\\WorkDir\\b\\komsomols_work\\build-Interface-Desktop_Qt_6_5_0_MinGW_64_bit-Debug","-IG:\\Games\\6.5.0\\mingw_64\\mkspecs\\win32-g++","-isystem","G:\\Games\\Tools\\mingw1120_64\\lib\\gcc\\x86_64-w64-mingw32\\11.2.0\\include\\c++","-isystem","G:\\Games\\Tools\\mingw1120_64\\lib\\gcc\\x86_64-w64-mingw32\\11.2.0\\include\\c++\\x86_64-w64-mingw32","-isystem","G:\\Games\\Tools\\mingw1120_64\\lib\\gcc\\x86_64-w64-mingw32\\11.2.0\\include\\c++\\backward","-isystem","G:\\Games\\Tools\\QtCreator\\bin\\clang\\lib\\clang\\15.0.0\\include","-isystem","G:\\Games\\Tools\\mingw1120_64\\x86_64-w64-mingw32\\include","-fmessage-length=0","-fdiagnostics-show-note-include-stack","-fretain-comments-from-system-headers","-fmacro-backtrace-limit=0","-ferror-limit=1000","-x","c++-header","C:\\WorkDir\\b\\komsomols_work\\build-Interface-Desktop_Qt_6_5_0_MinGW_64_bit-Debug\\ui_mainwindow.h"],"directory":"C:/WorkDir/b/komsomols_work/build-Interface-Desktop_Qt_6_5_0_MinGW_64_bit-Debug/.qtc_clangd","file":"C:/WorkDir/b/komsomols_work/build-Interface-Desktop_Qt_6_5_0_MinGW_64_bit-Debug/ui_mainwindow.h"},{"arguments":["clang","-Wno-documentation-unknown-command","-Wno-unknown-warning-option","-Wno-unknown-pragmas","-nostdinc","-nostdinc++","-g","-std=gnu++1z","-Wall","-Wextra","-Wextra","-fexceptions","-mthreads","-fsyntax-only","-m64","--target=x86_64-w64-mingw32","-DUNICODE","-D_UNICODE","-DWIN32","-DMINGW_HAS_SECURE_API","-DQT_QML_DEBUG","-DQT_WIDGETS_LIB","-DQT_GUI_LIB","-DQT_NETWORK_LIB","-DQT_CORE_LIB","-DQT_NEEDS_QMAIN","-DQ_CREATOR_RUN","-IG:\\Games\\Tools\\QtCreator\\share\\qtcreator\\cplusplus\\wrappedMingwHeaders","-IG:\\Games\\Tools\\QtCreator\\share\\qtcreator\\cplusplus\\wrappedQtHeaders","-IG:\\Games\\Tools\\QtCreator\\share\\qtcreator\\cplusplus\\wrappedQtHeaders\\QtCore","-IC:\\WorkDir\\b\\komsomols_work\\Interface","-IG:\\Games\\6.5.0\\mingw_64\\include","-IG:\\Games\\6.5.0\\mingw_64\\include\\QtWidgets","-IG:\\Games\\6.5.0\\mingw_64\\include\\QtGui","-IG:\\Games\\6.5.0\\mingw_64\\include\\QtNetwork","-IG:\\Games\\6.5.0\\mingw_64\\include\\QtCore","-IC:\\WorkDir\\b\\komsomols_work\\build-Interface-Desktop_Qt_6_5_0_MinGW_64_bit-Debug\\debug","-IC:\\WorkDir\\b\\komsomols_work\\build-Interface-Desktop_Qt_6_5_0_MinGW_64_bit-Debug","-IG:\\Games\\6.5.0\\mingw_64\\mkspecs\\win32-g++","-isystem","G:\\Games\\Tools\\mingw1120_64\\lib\\gcc\\x86_64-w64-mingw32\\11.2.0\\include\\c++","-isystem","G:\\Games\\Tools\\mingw1120_64\\lib\\gcc\\x86_64-w64-mingw32\\11.2.0\\include\\c++\\x86_64-w64-mingw32","-isystem","G:\\Games\\Tools\\mingw1120_64\\lib\\gcc\\x86_64-w64-mingw32\\11.2.0\\include\\c++\\backward","-isystem","G:\\Games\\Tools\\QtCreator\\bin\\clang\\lib\\clang\\15.0.0\\include","-isystem","G:\\Games\\Tools\\mingw1120_64\\x86_64-w64-mingw32\\include","-fmessage-length=0","-fdiagnostics-show-note-include-stack","-fretain-comments-from-system-headers","-fmacro-backtrace-limit=0","-ferror-limit=1000","-x","c++-header","C:\\WorkDir\\b\\komsomols_work\\build-Interface-Desktop_Qt_6_5_0_MinGW_64_bit-Debug\\ui_secondtask.h"],"directory":"C:/WorkDir/b/komsomols_work/build-Interface-Desktop_Qt_6_5_0_MinGW_64_bit-Debug/.qtc_clangd","file":"C:/WorkDir/b/komsomols_work/build-Interface-Desktop_Qt_6_5_0_MinGW_64_bit-Debug/ui_secondtask.h"},{"arguments":["clang","-Wno-documentation-unknown-command","-Wno-unknown-warning-option","-Wno-unknown-pragmas","-nostdinc","-nostdinc++","-g","-std=gnu++1z","-Wall","-Wextra","-Wextra","-fexceptions","-mthreads","-fsyntax-only","-m64","--target=x86_64-w64-mingw32","-DUNICODE","-D_UNICODE","-DWIN32","-DMINGW_HAS_SECURE_API","-DQT_QML_DEBUG","-DQT_WIDGETS_LIB","-DQT_GUI_LIB","-DQT_NETWORK_LIB","-DQT_CORE_LIB","-DQT_NEEDS_QMAIN","-DQ_CREATOR_RUN","-IG:\\Games\\Tools\\QtCreator\\share\\qtcreator\\cplusplus\\wrappedMingwHeaders","-IG:\\Games\\Tools\\QtCreator\\share\\qtcreator\\cplusplus\\wrappedQtHeaders","-IG:\\Games\\Tools\\QtCreator\\share\\qtcreator\\cplusplus\\wrappedQtHeaders\\QtCore","-IC:\\WorkDir\\b\\komsomols_work\\Interface","-IG:\\Games\\6.5.0\\mingw_64\\include","-IG:\\Games\\6.5.0\\mingw_64\\include\\QtWidgets","-IG:\\Games\\6.5.0\\mingw_64\\include\\QtGui","-IG:\\Games\\6.5.0\\mingw_64\\include\\QtNetwork","-IG:\\Games\\6.5.0\\mingw_64\\include\\QtCore","-IC:\\WorkDir\\b\\komsomols_work\\build-Interface-Desktop_Qt_6_5_0_MinGW_64_bit-Debug\\debug","-IC:\\WorkDir\\b\\komsomols_work\\build-Interface-Desktop_Qt_6_5_0_MinGW_64_bit-Debug","-IG:\\Games\\6.5.0\\mingw_64\\mkspecs\\win32-g++","-isystem","G:\\Games\\Tools\\mingw1120_64\\lib\\gcc\\x86_64-w64-mingw32\\11.2.0\\include\\c++","-isystem","G:\\Games\\Tools\\mingw1120_64\\lib\\gcc\\x86_64-w64-mingw32\\11.2.0\\include\\c++\\x86_64-w64-mingw32","-isystem","G:\\Games\\Tools\\mingw1120_64\\lib\\gcc\\x86_64-w64-mingw32\\11.2.0\\include\\c++\\backward","-isystem","G:\\Games\\Tools\\QtCreator\\bin\\clang\\lib\\clang\\15.0.0\\include","-isystem","G:\\Games\\Tools\\mingw1120_64\\x86_64-w64-mingw32\\include","-fmessage-length=0","-fdiagnostics-show-note-include-stack","-fretain-comments-from-system-headers","-fmacro-backtrace-limit=0","-ferror-limit=1000","-x","c++-header","C:\\WorkDir\\b\\komsomols_work\\build-Interface-Desktop_Qt_6_5_0_MinGW_64_bit-Debug\\ui_registration.h"],"directory":"C:/WorkDir/b/komsomols_work/build-Interface-Desktop_Qt_6_5_0_MinGW_64_bit-Debug/.qtc_clangd","file":"C:/WorkDir/b/komsomols_work/build-Interface-Desktop_Qt_6_5_0_MinGW_64_bit-Debug/ui_registration.h"},{"arguments":["clang","-Wno-documentation-unknown-command","-Wno-unknown-warning-option","-Wno-unknown-pragmas","-nostdinc","-nostdinc++","-g","-std=gnu++1z","-Wall","-Wextra","-Wextra","-fexceptions","-mthreads","-fsyntax-only","-m64","--target=x86_64-w64-mingw32","-DUNICODE","-D_UNICODE","-DWIN32","-DMINGW_HAS_SECURE_API","-DQT_QML_DEBUG","-DQT_WIDGETS_LIB","-DQT_GUI_LIB","-DQT_NETWORK_LIB","-DQT_CORE_LIB","-DQT_NEEDS_QMAIN","-DQ_CREATOR_RUN","-IG:\\Games\\Tools\\QtCreator\\share\\qtcreator\\cplusplus\\wrappedMingwHeaders","-IG:\\Games\\Tools\\QtCreator\\share\\qtcreator\\cplusplus\\wrappedQtHeaders","-IG:\\Games\\Tools\\QtCreator\\share\\qtcreator\\cplusplus\\wrappedQtHeaders\\QtCore","-IC:\\WorkDir\\b\\komsomols_work\\Interface","-IG:\\Games\\6.5.0\\mingw_64\\include","-IG:\\Games\\6.5.0\\mingw_64\\include\\QtWidgets","-IG:\\Games\\6.5.0\\mingw_64\\include\\QtGui","-IG:\\Games\\6.5.0\\mingw_64\\include\\QtNetwork","-IG:\\Games\\6.5.0\\mingw_64\\include\\QtCore","-IC:\\WorkDir\\b\\komsomols_work\\build-Interface-Desktop_Qt_6_5_0_MinGW_64_bit-Debug\\debug","-IC:\\WorkDir\\b\\komsomols_work\\build-Interface-Desktop_Qt_6_5_0_MinGW_64_bit-Debug","-IG:\\Games\\6.5.0\\mingw_64\\mkspecs\\win32-g++","-isystem","G:\\Games\\Tools\\mingw1120_64\\lib\\gcc\\x86_64-w64-mingw32\\11.2.0\\include\\c++","-isystem","G:\\Games\\Tools\\mingw1120_64\\lib\\gcc\\x86_64-w64-mingw32\\11.2.0\\include\\c++\\x86_64-w64-mingw32","-isystem","G:\\Games\\Tools\\mingw1120_64\\lib\\gcc\\x86_64-w64-mingw32\\11.2.0\\include\\c++\\backward","-isystem","G:\\Games\\Tools\\QtCreator\\bin\\clang\\lib\\clang\\15.0.0\\include","-isystem","G:\\Games\\Tools\\mingw1120_64\\x86_64-w64-mingw32\\include","-fmessage-length=0","-fdiagnostics-show-note-include-stack","-fretain-comments-from-system-headers","-fmacro-backtrace-limit=0","-ferror-limit=1000","-x","c++-header","C:\\WorkDir\\b\\komsomols_work\\build-Interface-Desktop_Qt_6_5_0_MinGW_64_bit-Debug\\ui_taskswindow.h"],"directory":"C:/WorkDir/b/komsomols_work/build-Interface-Desktop_Qt_6_5_0_MinGW_64_bit-Debug/.qtc_clangd","file":"C:/WorkDir/b/komsomols_work/build-Interface-Desktop_Qt_6_5_0_MinGW_64_bit-Debug/ui_taskswindow.h"}]